rosys/.syncignore
rosys/__init__.py
rosys/analysis/__init__.py
rosys/analysis/assets/RobotoMono-Medium.ttf
rosys/analysis/asyncio_warnings.py
rosys/analysis/kpi_buckets.py
rosys/analysis/kpi_chart.py
rosys/analysis/kpi_logger.py
rosys/analysis/kpi_page_.py
rosys/analysis/legacy/__init__.py
rosys/analysis/legacy/asyncio_monitor.py
rosys/analysis/legacy/asyncio_page.py
rosys/analysis/legacy/network_monitor.py
rosys/analysis/legacy/objgraph_page.py
rosys/analysis/legacy/pyloot_page.py
rosys/analysis/logging_page.py
rosys/analysis/logs_page_.py
rosys/analysis/memory.py
rosys/analysis/profile_button_.py
rosys/analysis/profiling.py
rosys/analysis/timelapse_recorder.py
rosys/analysis/tracking.py
rosys/analysis/videos_page_.py
rosys/automation/__init__.py
rosys/automation/app_controls_.py
rosys/automation/automation.py
rosys/automation/automation_controls_.py
rosys/automation/automator.py
rosys/automation/parallelize.py
rosys/automation/schedule.py
rosys/config.py
rosys/core.py
rosys/driving/__init__.py
rosys/driving/drivable.py
rosys/driving/driver.py
rosys/driving/driver_object.py
rosys/driving/joystick_.py
rosys/driving/keyboard_control_.py
rosys/driving/odometer.py
rosys/driving/path_segment.py
rosys/driving/robot_object_.py
rosys/driving/steerer.py
rosys/geometry/__init__.py
rosys/geometry/frame3d_registry.py
rosys/geometry/geo.py
rosys/geometry/line.py
rosys/geometry/line_segment.py
rosys/geometry/object3d.py
rosys/geometry/point.py
rosys/geometry/point3d.py
rosys/geometry/polygon.py
rosys/geometry/pose.py
rosys/geometry/pose3d.py
rosys/geometry/prism.py
rosys/geometry/rectangle.py
rosys/geometry/rotation.py
rosys/geometry/spline.py
rosys/geometry/velocity.py
rosys/hardware/__init__.py
rosys/hardware/battery_control.py
rosys/hardware/bluetooth.py
rosys/hardware/bms.py
rosys/hardware/bms_message.py
rosys/hardware/bms_state.py
rosys/hardware/bumper.py
rosys/hardware/can.py
rosys/hardware/communication/__init__.py
rosys/hardware/communication/communication.py
rosys-0.32.0.dist-info/METADATA
rosys-0.32.0.dist-info/WHEEL
rosys-0.32.0.dist-info/entry_points.txt
rosys-0.32.0.dist-info/licenses/LICENSE
rosys-0.32.0.dist-info/RECORD
