Metadata-Version: 2.4
Name: rosys
Version: 0.32.0
Summary: Modular Robot System With Elegant Automation Capabilities
License: MIT
License-File: LICENSE
Keywords: robot,framework,automation,control,steer
Author: Zauberzeug GmbH
Author-email: info@zauberzeug.com
Requires-Python: >=3.11,<3.14
Classifier: License :: OSI Approved :: MIT License
Classifier: Programming Language :: Python :: 3
Classifier: Programming Language :: Python :: 3.11
Classifier: Programming Language :: Python :: 3.12
Classifier: Programming Language :: Python :: 3.13
Requires-Dist: aiohttp (>=3.13.3)
Requires-Dist: cairosvg (>=2.7.0,<3.0.0)
Requires-Dist: coloredlogs (>=15.0.1,<16.0.0)
Requires-Dist: dataclasses-json (>=0.5.7,<0.6.0)
Requires-Dist: fonttools (>=4.60.2,<5.0.0)
Requires-Dist: httpx (>=0.25.0)
Requires-Dist: humanize (>=4.0.0,<5.0.0)
Requires-Dist: idna (>=3.7)
Requires-Dist: ifaddr (>=0.2.0,<0.3.0)
Requires-Dist: imgsize (>=2.1,<3.0)
Requires-Dist: line-profiler (>=4.1.3,<5.0.0)
Requires-Dist: marshmallow (>=3.26.2,<4.0.0)
Requires-Dist: matplotlib (>=3.7.2,<4.0.0)
Requires-Dist: networkx (>=2.6.2,<3.0.0)
Requires-Dist: nicegui (>=3.4.0,<4.0.0)
Requires-Dist: numpy (<3.0.0)
Requires-Dist: objgraph (>=3.6.1,<4.0.0)
Requires-Dist: opencv-contrib-python (>=4.12.0.88,<4.13.0.0)
Requires-Dist: pillow (>=11.3.0)
Requires-Dist: psutil (>=5.9.0,<6.0.0)
Requires-Dist: pyloot (>=0.1.0,<0.2.0)
Requires-Dist: pyquaternion (>=0.9.9,<0.10.0)
Requires-Dist: pyserial (>=3.5,<4.0)
Requires-Dist: pyturbojpeg (>=1.8.2,<2.0.0)
Requires-Dist: pyudev (>=0.21.0)
Requires-Dist: requests (>=2.32.4)
Requires-Dist: scipy (>=1.7.2,<2.0.0)
Requires-Dist: starlette (>=0.49.1)
Requires-Dist: suntime (>=1.2.5,<2.0.0)
Requires-Dist: tabulate (>=0.8.9,<0.9.0)
Requires-Dist: urllib3 (>=2.6.3)
Requires-Dist: uvicorn (!=0.29.0)
Requires-Dist: uvloop (>=0.17.0)
Requires-Dist: yappi (>=1.6.0,<2.0.0)
Project-URL: Repository, https://github.com/zauberzeug/rosys
